{
  "content": "**Mittel-Dalmatien Marknadsrapport 2025**\n\n**Sammanfattning**\nMarknadssituationen i Mittel-Dalmatien under 2025 är fortsatt stabil med en ökad efterfrågan på fastigheter. Priserna har generellt sett ökat något jämfört med föregående år, vilket indikerar en fortsatt positiv utveckling på marknaden.\n\n**Prisanalys**\n• Genomsnittligt pris/m²: €3,000-4,500\n• Prisintervall: lågt-högt\n• Trend jämfört med föregående år: Stigande\n\n**Utbud & Efterfrågan**\n• Efterfrågan: inhemsk vs utländsk\n• Utbudssituation: Balanserad\n\n**Regionala Höjdpunkter**\nStäder: Split, Trogir, Makarska, Hvar\n\n**Köparprofil**\n• Typiska köpare: Utländska investerare och semestergäster\n• Motiv: Investering, semesterboende\n\n**Utsikter**\nKortfristiga förväntningar är att marknaden kommer att fortsätta att vara stabil med en fortsatt ökning av efterfrågan och priserna.\n\n**Nyckeldata**\n• Faktum 1\n• Faktum 2\n• Faktum 3\n\n**Senast Uppdaterad: Januari 2025**",
  "region": "dalmatien-mitte",
  "region_name": "Mellersta Dalmatien",
  "year": 2025,
  "slug": "dalmatien-mitte-2025"
}