{
  "content": "**Обзор Рынка Slavonien 2025**\n\n**Резюме**\nНа рынке недвижимости в Славонии в 2025 году наблюдается стабильная ситуация. Цены остаются на уровне прошлого года, спрос и предложение также остаются на уровне, несмотря на некоторое увеличение иностранного спроса.\n\n**Анализ Цен**\n• Средняя цена за квадратный метр: €1,000-1,800\n• Диапазон цен: от низких до высоких\n• Тенденция по сравнению с прошлым годом: стабильная\n\n**Спрос и Предложение**\n• Спрос: внутренний vs иностранный\n• Ситуация с предложением: удовлетворительная\n\n**Региональный Обзор**\nГорода: Осиек, Вуковар\n\n**Профиль Покупателя**\n• Типичные покупатели: местные жители, иностранные инвесторы\n• Мотивации: жилье для проживания, инвестиции\n\n**Прогноз**\nОжидается стабильное развитие рынка недвижимости в Славонии в ближайшем будущем.\n\n**Ключевые Данные**\n• Факт 1\n• Факт 2\n• Факт 3\n\n**Последнее Обновление: Январь 2025**",
  "region": "slavonien",
  "region_name": "Славония",
  "year": 2025,
  "slug": "slavonien-2025"
}