{
  "content": "**Slavonien Marktbericht 2025**\n\n**Zusammenfassung**\nDer Immobilienmarkt in Slavonien verzeichnet im Jahr 2025 eine stabile Situation mit einem durchschnittlichen Preis pro Quadratmeter von €X,XXX-X,XXX. Im Vergleich zum Vorjahr zeigt sich ein leichter Anstieg der Preise.\n\n**Preisanalyse**\n• Durchschnittlicher Preis/m²: €X,XXX-X,XXX\n• Preisspanne: niedrig-hoch\n• Trend im Vergleich zum Vorjahr: steigend\n\n**Angebot & Nachfrage**\n• Nachfrage: Inlands- vs. Auslandskäufer\n• Angebotssituation\n\n**Regionale Highlights**\nStädte: Osijek, Vukovar\n\n**Käufer- & Investorenprofil**\n• Typische Käufer\n• Motivationen\n\n**Ausblick**\nKurzfristige Erwartungen deuten auf eine weiterhin stabile Entwicklung des Marktes hin.\n\n**Wichtige Daten**\n• Fakt 1\n• Fakt 2\n• Fakt 3\n\n**Letztes Update: Januar 2025**\n\nVerwenden Sie realistische kroatische Preise: Küste €2.500-5.000/m², Zagreb €2.000-3.500/m², Binnenland €800-1.500/m².",
  "region": "slavonien",
  "region_name": "Slavonien",
  "year": 2025,
  "slug": "slavonien-2025"
}